[
  {
    "Exam": "Mathematics ",
    "Roll No": "014",
    "Correct Answers": "50",
    "Incorrect Answers": "0",
    "Not attempted": "0",
    "Math": "50.0",
    "Total Marks": "50.0",
    "Rank": "1"
  },
  {
    "Exam": "Mathematics ",
    "Roll No": "016",
    "Correct Answers": "50",
    "Incorrect Answers": "0",
    "Not attempted": "0",
    "Math": "50.0",
    "Total Marks": "50.0",
    "Rank": "1"
  },
  {
    "Exam": "Mathematics ",
    "Roll No": "022",
    "Correct Answers": "50",
    "Incorrect Answers": "0",
    "Not attempted": "0",
    "Math": "50.0",
    "Total Marks": "50.0",
    "Rank": "1"
  },
  {
    "Exam": "Mathematics ",
    "Roll No": "028",
    "Correct Answers": "50",
    "Incorrect Answers": "0",
    "Not attempted": "0",
    "Math": "50.0",
    "Total Marks": "50.0",
    "Rank": "1"
  },
  {
    "Exam": "Mathematics ",
    "Roll No": "033",
    "Correct Answers": "50",
    "Incorrect Answers": "0",
    "Not attempted": "0",
    "Math": "50.0",
    "Total Marks": "50.0",
    "Rank": "1"
  },
  {
    "Exam": "Mathematics ",
    "Roll No": "038",
    "Correct Answers": "50",
    "Incorrect Answers": "0",
    "Not attempted": "0",
    "Math": "50.0",
    "Total Marks": "50.0",
    "Rank": "1"
  },
  {
    "Exam": "Mathematics ",
    "Roll No": "049",
    "Correct Answers": "50",
    "Incorrect Answers": "0",
    "Not attempted": "0",
    "Math": "50.0",
    "Total Marks": "50.0",
    "Rank": "1"
  },
  {
    "Exam": "Mathematics ",
    "Roll No": "054",
    "Correct Answers": "50",
    "Incorrect Answers": "0",
    "Not attempted": "0",
    "Math": "50.0",
    "Total Marks": "50.0",
    "Rank": "1"
  },
  {
    "Exam": "Mathematics ",
    "Roll No": "061",
    "Correct Answers": "50",
    "Incorrect Answers": "0",
    "Not attempted": "0",
    "Math": "50.0",
    "Total Marks": "50.0",
    "Rank": "1"
  },
  {
    "Exam": "Mathematics ",
    "Roll No": "067",
    "Correct Answers": "50",
    "Incorrect Answers": "0",
    "Not attempted": "0",
    "Math": "50.0",
    "Total Marks": "50.0",
    "Rank": "1"
  },
  {
    "Exam": "Mathematics ",
    "Roll No": "079",
    "Correct Answers": "50",
    "Incorrect Answers": "0",
    "Not attempted": "0",
    "Math": "50.0",
    "Total Marks": "50.0",
    "Rank": "1"
  },
  {
    "Exam": "Mathematics ",
    "Roll No": "084",
    "Correct Answers": "50",
    "Incorrect Answers": "0",
    "Not attempted": "0",
    "Math": "50.0",
    "Total Marks": "50.0",
    "Rank": "1"
  },
  {
    "Exam": "Mathematics ",
    "Roll No": "092",
    "Correct Answers": "50",
    "Incorrect Answers": "0",
    "Not attempted": "0",
    "Math": "50.0",
    "Total Marks": "50.0",
    "Rank": "1"
  },
  {
    "Exam": "Mathematics ",
    "Roll No": "095",
    "Correct Answers": "50",
    "Incorrect Answers": "0",
    "Not attempted": "0",
    "Math": "50.0",
    "Total Marks": "50.0",
    "Rank": "1"
  },
  {
    "Exam": "Mathematics ",
    "Roll No": "002",
    "Correct Answers": "49",
    "Incorrect Answers": "1",
    "Not attempted": "0",
    "Math": "49.0",
    "Total Marks": "49.0",
    "Rank": "15"
  },
  {
    "Exam": "Mathematics ",
    "Roll No": "006",
    "Correct Answers": "49",
    "Incorrect Answers": "1",
    "Not attempted": "0",
    "Math": "49.0",
    "Total Marks": "49.0",
    "Rank": "15"
  },
  {
    "Exam": "Mathematics ",
    "Roll No": "008",
    "Correct Answers": "49",
    "Incorrect Answers": "1",
    "Not attempted": "0",
    "Math": "49.0",
    "Total Marks": "49.0",
    "Rank": "15"
  },
  {
    "Exam": "Mathematics ",
    "Roll No": "010",
    "Correct Answers": "49",
    "Incorrect Answers": "1",
    "Not attempted": "0",
    "Math": "49.0",
    "Total Marks": "49.0",
    "Rank": "15"
  },
  {
    "Exam": "Mathematics ",
    "Roll No": "027",
    "Correct Answers": "49",
    "Incorrect Answers": "1",
    "Not attempted": "0",
    "Math": "49.0",
    "Total Marks": "49.0",
    "Rank": "15"
  },
  {
    "Exam": "Mathematics ",
    "Roll No": "032",
    "Correct Answers": "49",
    "Incorrect Answers": "1",
    "Not attempted": "0",
    "Math": "49.0",
    "Total Marks": "49.0",
    "Rank": "15"
  },
  {
    "Exam": "Mathematics ",
    "Roll No": "056",
    "Correct Answers": "49",
    "Incorrect Answers": "1",
    "Not attempted": "0",
    "Math": "49.0",
    "Total Marks": "49.0",
    "Rank": "15"
  },
  {
    "Exam": "Mathematics ",
    "Roll No": "082",
    "Correct Answers": "49",
    "Incorrect Answers": "1",
    "Not attempted": "0",
    "Math": "49.0",
    "Total Marks": "49.0",
    "Rank": "15"
  },
  {
    "Exam": "Mathematics ",
    "Roll No": "101",
    "Correct Answers": "49",
    "Incorrect Answers": "1",
    "Not attempted": "0",
    "Math": "49.0",
    "Total Marks": "49.0",
    "Rank": "15"
  },
  {
    "Exam": "Mathematics ",
    "Roll No": "120",
    "Correct Answers": "49",
    "Incorrect Answers": "1",
    "Not attempted": "0",
    "Math": "49.0",
    "Total Marks": "49.0",
    "Rank": "15"
  },
  {
    "Exam": "Mathematics ",
    "Roll No": "128",
    "Correct Answers": "49",
    "Incorrect Answers": "1",
    "Not attempted": "0",
    "Math": "49.0",
    "Total Marks": "49.0",
    "Rank": "15"
  },
  {
    "Exam": "Mathematics ",
    "Roll No": "011",
    "Correct Answers": "48",
    "Incorrect Answers": "2",
    "Not attempted": "0",
    "Math": "48.0",
    "Total Marks": "48.0",
    "Rank": "26"
  },
  {
    "Exam": "Mathematics ",
    "Roll No": "012",
    "Correct Answers": "48",
    "Incorrect Answers": "2",
    "Not attempted": "0",
    "Math": "48.0",
    "Total Marks": "48.0",
    "Rank": "26"
  },
  {
    "Exam": "Mathematics ",
    "Roll No": "023",
    "Correct Answers": "48",
    "Incorrect Answers": "2",
    "Not attempted": "0",
    "Math": "48.0",
    "Total Marks": "48.0",
    "Rank": "26"
  },
  {
    "Exam": "Mathematics ",
    "Roll No": "040",
    "Correct Answers": "48",
    "Incorrect Answers": "2",
    "Not attempted": "0",
    "Math": "48.0",
    "Total Marks": "48.0",
    "Rank": "26"
  },
  {
    "Exam": "Mathematics ",
    "Roll No": "041",
    "Correct Answers": "48",
    "Incorrect Answers": "2",
    "Not attempted": "0",
    "Math": "48.0",
    "Total Marks": "48.0",
    "Rank": "26"
  },
  {
    "Exam": "Mathematics ",
    "Roll No": "043",
    "Correct Answers": "48",
    "Incorrect Answers": "2",
    "Not attempted": "0",
    "Math": "48.0",
    "Total Marks": "48.0",
    "Rank": "26"
  },
  {
    "Exam": "Mathematics ",
    "Roll No": "051",
    "Correct Answers": "48",
    "Incorrect Answers": "2",
    "Not attempted": "0",
    "Math": "48.0",
    "Total Marks": "48.0",
    "Rank": "26"
  },
  {
    "Exam": "Mathematics ",
    "Roll No": "075",
    "Correct Answers": "48",
    "Incorrect Answers": "2",
    "Not attempted": "0",
    "Math": "48.0",
    "Total Marks": "48.0",
    "Rank": "26"
  },
  {
    "Exam": "Mathematics ",
    "Roll No": "076",
    "Correct Answers": "48",
    "Incorrect Answers": "1",
    "Not attempted": "1",
    "Math": "48.0",
    "Total Marks": "48.0",
    "Rank": "26"
  },
  {
    "Exam": "Mathematics ",
    "Roll No": "113",
    "Correct Answers": "48",
    "Incorrect Answers": "1",
    "Not attempted": "1",
    "Math": "48.0",
    "Total Marks": "48.0",
    "Rank": "26"
  },
  {
    "Exam": "Mathematics ",
    "Roll No": "035",
    "Correct Answers": "47",
    "Incorrect Answers": "3",
    "Not attempted": "0",
    "Math": "47.0",
    "Total Marks": "47.0",
    "Rank": "36"
  },
  {
    "Exam": "Mathematics ",
    "Roll No": "036",
    "Correct Answers": "47",
    "Incorrect Answers": "2",
    "Not attempted": "1",
    "Math": "47.0",
    "Total Marks": "47.0",
    "Rank": "36"
  },
  {
    "Exam": "Mathematics ",
    "Roll No": "047",
    "Correct Answers": "47",
    "Incorrect Answers": "3",
    "Not attempted": "0",
    "Math": "47.0",
    "Total Marks": "47.0",
    "Rank": "36"
  },
  {
    "Exam": "Mathematics ",
    "Roll No": "078",
    "Correct Answers": "47",
    "Incorrect Answers": "2",
    "Not attempted": "1",
    "Math": "47.0",
    "Total Marks": "47.0",
    "Rank": "36"
  },
  {
    "Exam": "Mathematics ",
    "Roll No": "087",
    "Correct Answers": "47",
    "Incorrect Answers": "1",
    "Not attempted": "2",
    "Math": "47.0",
    "Total Marks": "47.0",
    "Rank": "36"
  },
  {
    "Exam": "Mathematics ",
    "Roll No": "004",
    "Correct Answers": "46",
    "Incorrect Answers": "4",
    "Not attempted": "0",
    "Math": "46.0",
    "Total Marks": "46.0",
    "Rank": "41"
  },
  {
    "Exam": "Mathematics ",
    "Roll No": "025",
    "Correct Answers": "46",
    "Incorrect Answers": "4",
    "Not attempted": "0",
    "Math": "46.0",
    "Total Marks": "46.0",
    "Rank": "41"
  },
  {
    "Exam": "Mathematics ",
    "Roll No": "081",
    "Correct Answers": "46",
    "Incorrect Answers": "4",
    "Not attempted": "0",
    "Math": "46.0",
    "Total Marks": "46.0",
    "Rank": "41"
  },
  {
    "Exam": "Mathematics ",
    "Roll No": "118",
    "Correct Answers": "45",
    "Incorrect Answers": "5",
    "Not attempted": "0",
    "Math": "45.0",
    "Total Marks": "45.0",
    "Rank": "44"
  },
  {
    "Exam": "Mathematics ",
    "Roll No": "030",
    "Correct Answers": "44",
    "Incorrect Answers": "6",
    "Not attempted": "0",
    "Math": "44.0",
    "Total Marks": "44.0",
    "Rank": "45"
  },
  {
    "Exam": "Mathematics ",
    "Roll No": "037",
    "Correct Answers": "44",
    "Incorrect Answers": "5",
    "Not attempted": "1",
    "Math": "44.0",
    "Total Marks": "44.0",
    "Rank": "45"
  },
  {
    "Exam": "Mathematics ",
    "Roll No": "050",
    "Correct Answers": "44",
    "Incorrect Answers": "5",
    "Not attempted": "1",
    "Math": "44.0",
    "Total Marks": "44.0",
    "Rank": "45"
  },
  {
    "Exam": "Mathematics ",
    "Roll No": "070",
    "Correct Answers": "44",
    "Incorrect Answers": "1",
    "Not attempted": "5",
    "Math": "44.0",
    "Total Marks": "44.0",
    "Rank": "45"
  },
  {
    "Exam": "Mathematics ",
    "Roll No": "097",
    "Correct Answers": "44",
    "Incorrect Answers": "5",
    "Not attempted": "1",
    "Math": "44.0",
    "Total Marks": "44.0",
    "Rank": "45"
  },
  {
    "Exam": "Mathematics ",
    "Roll No": "123",
    "Correct Answers": "44",
    "Incorrect Answers": "6",
    "Not attempted": "0",
    "Math": "44.0",
    "Total Marks": "44.0",
    "Rank": "45"
  },
  {
    "Exam": "Mathematics ",
    "Roll No": "013",
    "Correct Answers": "43",
    "Incorrect Answers": "7",
    "Not attempted": "0",
    "Math": "43.0",
    "Total Marks": "43.0",
    "Rank": "51"
  },
  {
    "Exam": "Mathematics ",
    "Roll No": "034",
    "Correct Answers": "43",
    "Incorrect Answers": "7",
    "Not attempted": "0",
    "Math": "43.0",
    "Total Marks": "43.0",
    "Rank": "51"
  },
  {
    "Exam": "Mathematics ",
    "Roll No": "121",
    "Correct Answers": "43",
    "Incorrect Answers": "7",
    "Not attempted": "0",
    "Math": "43.0",
    "Total Marks": "43.0",
    "Rank": "51"
  },
  {
    "Exam": "Mathematics ",
    "Roll No": "127",
    "Correct Answers": "43",
    "Incorrect Answers": "7",
    "Not attempted": "0",
    "Math": "43.0",
    "Total Marks": "43.0",
    "Rank": "51"
  },
  {
    "Exam": "Mathematics ",
    "Roll No": "099",
    "Correct Answers": "41",
    "Incorrect Answers": "9",
    "Not attempted": "0",
    "Math": "41.0",
    "Total Marks": "41.0",
    "Rank": "55"
  },
  {
    "Exam": "Mathematics ",
    "Roll No": "122",
    "Correct Answers": "41",
    "Incorrect Answers": "9",
    "Not attempted": "0",
    "Math": "41.0",
    "Total Marks": "41.0",
    "Rank": "55"
  },
  {
    "Exam": "Mathematics ",
    "Roll No": "058",
    "Correct Answers": "40",
    "Incorrect Answers": "10",
    "Not attempted": "0",
    "Math": "40.0",
    "Total Marks": "40.0",
    "Rank": "57"
  },
  {
    "Exam": "Mathematics ",
    "Roll No": "096",
    "Correct Answers": "40",
    "Incorrect Answers": "10",
    "Not attempted": "0",
    "Math": "40.0",
    "Total Marks": "40.0",
    "Rank": "57"
  },
  {
    "Exam": "Mathematics ",
    "Roll No": "107",
    "Correct Answers": "40",
    "Incorrect Answers": "8",
    "Not attempted": "2",
    "Math": "40.0",
    "Total Marks": "40.0",
    "Rank": "57"
  },
  {
    "Exam": "Mathematics ",
    "Roll No": "031",
    "Correct Answers": "39",
    "Incorrect Answers": "10",
    "Not attempted": "1",
    "Math": "39.0",
    "Total Marks": "39.0",
    "Rank": "60"
  },
  {
    "Exam": "Mathematics ",
    "Roll No": "086",
    "Correct Answers": "39",
    "Incorrect Answers": "7",
    "Not attempted": "4",
    "Math": "39.0",
    "Total Marks": "39.0",
    "Rank": "60"
  },
  {
    "Exam": "Mathematics ",
    "Roll No": "129",
    "Correct Answers": "39",
    "Incorrect Answers": "11",
    "Not attempted": "0",
    "Math": "39.0",
    "Total Marks": "39.0",
    "Rank": "60"
  },
  {
    "Exam": "Mathematics ",
    "Roll No": "026",
    "Correct Answers": "38",
    "Incorrect Answers": "12",
    "Not attempted": "0",
    "Math": "38.0",
    "Total Marks": "38.0",
    "Rank": "63"
  },
  {
    "Exam": "Mathematics ",
    "Roll No": "065",
    "Correct Answers": "38",
    "Incorrect Answers": "12",
    "Not attempted": "0",
    "Math": "38.0",
    "Total Marks": "38.0",
    "Rank": "63"
  },
  {
    "Exam": "Mathematics ",
    "Roll No": "074",
    "Correct Answers": "37",
    "Incorrect Answers": "13",
    "Not attempted": "0",
    "Math": "37.0",
    "Total Marks": "37.0",
    "Rank": "65"
  },
  {
    "Exam": "Mathematics ",
    "Roll No": "003",
    "Correct Answers": "36",
    "Incorrect Answers": "14",
    "Not attempted": "0",
    "Math": "36.0",
    "Total Marks": "36.0",
    "Rank": "66"
  },
  {
    "Exam": "Mathematics ",
    "Roll No": "066",
    "Correct Answers": "36",
    "Incorrect Answers": "14",
    "Not attempted": "0",
    "Math": "36.0",
    "Total Marks": "36.0",
    "Rank": "66"
  },
  {
    "Exam": "Mathematics ",
    "Roll No": "090",
    "Correct Answers": "36",
    "Incorrect Answers": "14",
    "Not attempted": "0",
    "Math": "36.0",
    "Total Marks": "36.0",
    "Rank": "66"
  },
  {
    "Exam": "Mathematics ",
    "Roll No": "114",
    "Correct Answers": "36",
    "Incorrect Answers": "14",
    "Not attempted": "0",
    "Math": "36.0",
    "Total Marks": "36.0",
    "Rank": "66"
  },
  {
    "Exam": "Mathematics ",
    "Roll No": "019",
    "Correct Answers": "35",
    "Incorrect Answers": "15",
    "Not attempted": "0",
    "Math": "35.0",
    "Total Marks": "35.0",
    "Rank": "70"
  },
  {
    "Exam": "Mathematics ",
    "Roll No": "060",
    "Correct Answers": "35",
    "Incorrect Answers": "15",
    "Not attempted": "0",
    "Math": "35.0",
    "Total Marks": "35.0",
    "Rank": "70"
  },
  {
    "Exam": "Mathematics ",
    "Roll No": "089",
    "Correct Answers": "35",
    "Incorrect Answers": "15",
    "Not attempted": "0",
    "Math": "35.0",
    "Total Marks": "35.0",
    "Rank": "70"
  },
  {
    "Exam": "Mathematics ",
    "Roll No": "005",
    "Correct Answers": "32",
    "Incorrect Answers": "18",
    "Not attempted": "0",
    "Math": "32.0",
    "Total Marks": "32.0",
    "Rank": "73"
  },
  {
    "Exam": "Mathematics ",
    "Roll No": "017",
    "Correct Answers": "32",
    "Incorrect Answers": "18",
    "Not attempted": "0",
    "Math": "32.0",
    "Total Marks": "32.0",
    "Rank": "73"
  },
  {
    "Exam": "Mathematics ",
    "Roll No": "046",
    "Correct Answers": "31",
    "Incorrect Answers": "12",
    "Not attempted": "7",
    "Math": "31.0",
    "Total Marks": "31.0",
    "Rank": "75"
  },
  {
    "Exam": "Mathematics ",
    "Roll No": "068",
    "Correct Answers": "31",
    "Incorrect Answers": "19",
    "Not attempted": "0",
    "Math": "31.0",
    "Total Marks": "31.0",
    "Rank": "75"
  },
  {
    "Exam": "Mathematics ",
    "Roll No": "116",
    "Correct Answers": "31",
    "Incorrect Answers": "18",
    "Not attempted": "1",
    "Math": "31.0",
    "Total Marks": "31.0",
    "Rank": "75"
  },
  {
    "Exam": "Mathematics ",
    "Roll No": "062",
    "Correct Answers": "29",
    "Incorrect Answers": "21",
    "Not attempted": "0",
    "Math": "29.0",
    "Total Marks": "29.0",
    "Rank": "78"
  },
  {
    "Exam": "Mathematics ",
    "Roll No": "042",
    "Correct Answers": "28",
    "Incorrect Answers": "20",
    "Not attempted": "2",
    "Math": "28.0",
    "Total Marks": "28.0",
    "Rank": "79"
  },
  {
    "Exam": "Mathematics ",
    "Roll No": "125",
    "Correct Answers": "28",
    "Incorrect Answers": "20",
    "Not attempted": "2",
    "Math": "28.0",
    "Total Marks": "28.0",
    "Rank": "79"
  },
  {
    "Exam": "Mathematics ",
    "Roll No": "021",
    "Correct Answers": "27",
    "Incorrect Answers": "23",
    "Not attempted": "0",
    "Math": "27.0",
    "Total Marks": "27.0",
    "Rank": "81"
  },
  {
    "Exam": "Mathematics ",
    "Roll No": "124",
    "Correct Answers": "17",
    "Incorrect Answers": "33",
    "Not attempted": "0",
    "Math": "17.0",
    "Total Marks": "17.0",
    "Rank": "82"
  }
]